maltego_trx/__init__.py
maltego_trx/commands.py
maltego_trx/decorator_registry.py
maltego_trx/entities.py
maltego_trx/handler.py
maltego_trx/maltego.py
maltego_trx/mtz.py
maltego_trx/oauth.py
maltego_trx/overlays.py
maltego_trx/registry.py
maltego_trx/server.py
maltego_trx/transform.py
maltego_trx/utils.py
maltego_trx/template_dir/Dockerfile
maltego_trx/template_dir/docker-compose.yml
maltego_trx/template_dir/extensions.py
maltego_trx/template_dir/project.py
maltego_trx/template_dir/requirements.txt
maltego_trx/template_dir/settings.csv
maltego_trx/template_dir/settings.py
maltego_trx/template_dir/transforms.csv
maltego_trx/template_dir/transforms/DNSToIP.py
maltego_trx/template_dir/transforms/GreetPerson.py
maltego_trx/template_dir/transforms/GreetPersonLocalized.py
maltego_trx/template_dir/transforms/OverlayExample.py
maltego_trx/template_dir/transforms/__init__.py
maltego_trx-1.6.1.dist-info/LICENSE
maltego_trx-1.6.1.dist-info/METADATA
maltego_trx-1.6.1.dist-info/WHEEL
maltego_trx-1.6.1.dist-info/entry_points.txt
maltego_trx-1.6.1.dist-info/top_level.txt
maltego_trx-1.6.1.dist-info/RECORD
