Metadata-Version: 2.1
Name: maltego-trx
Version: 1.6.1
Summary: Python library used to develop Maltego transforms
Home-page: https://github.com/paterva/maltego-trx/
Author: Maltego Staff
Author-email: support@maltego.com
License: MIT
Requires-Python: >=3.8.0
License-File: LICENSE
Requires-Dist: flask (>=2.2.0)
Requires-Dist: cryptography (>=39.0.1)
